odoo8_addon_medical_pharmacy-8.0.1.1.0.99.dev4-py2.7-nspkg.pth
odoo8_addon_medical_pharmacy-8.0.1.1.0.99.dev4.dist-info/DESCRIPTION.rst
odoo8_addon_medical_pharmacy-8.0.1.1.0.99.dev4.dist-info/METADATA
odoo8_addon_medical_pharmacy-8.0.1.1.0.99.dev4.dist-info/RECORD
odoo8_addon_medical_pharmacy-8.0.1.1.0.99.dev4.dist-info/WHEEL
odoo8_addon_medical_pharmacy-8.0.1.1.0.99.dev4.dist-info/metadata.json
odoo8_addon_medical_pharmacy-8.0.1.1.0.99.dev4.dist-info/namespace_packages.txt
odoo8_addon_medical_pharmacy-8.0.1.1.0.99.dev4.dist-info/top_level.txt
odoo_addons/medical_pharmacy/README.rst
odoo_addons/medical_pharmacy/__init__.py
odoo_addons/medical_pharmacy/__openerp__.py
odoo_addons/medical_pharmacy/i18n/pt_BR.po
odoo_addons/medical_pharmacy/i18n/sl.po
odoo_addons/medical_pharmacy/models/__init__.py
odoo_addons/medical_pharmacy/models/medical_pharmacy.py
odoo_addons/medical_pharmacy/security/ir.model.access.csv
odoo_addons/medical_pharmacy/views/medical_menu.xml
odoo_addons/medical_pharmacy/views/medical_pharmacy_view.xml
